reliably_app-0.5.0.data/data/docs/README.md
reliably_app-0.5.0.dist-info/METADATA
reliably_app-0.5.0.dist-info/WHEEL
reliably_app-0.5.0.dist-info/entry_points.txt
reliably_app/__init__.py
reliably_app/__version__.py
reliably_app/account/__init__.py
reliably_app/account/crud.py
reliably_app/account/errors.py
reliably_app/account/models.py
reliably_app/account/schemas.py
reliably_app/account/service.py
reliably_app/account/validators.py
reliably_app/agent/__init__.py
reliably_app/agent/crud.py
reliably_app/agent/errors.py
reliably_app/agent/models.py
reliably_app/agent/schemas.py
reliably_app/agent/service.py
reliably_app/agent/validators.py
reliably_app/assistant/__init__.py
reliably_app/assistant/crud.py
reliably_app/assistant/models.py
reliably_app/assistant/schemas.py
reliably_app/assistant/service.py
reliably_app/assistant/tasks/__init__.py
reliably_app/assistant/tasks/experiment.py
reliably_app/assistant/tasks/scenario.py
reliably_app/assistant/validators.py
reliably_app/auth/middlewares.py
reliably_app/background.py
reliably_app/catalog/__init__.py
reliably_app/catalog/crud.py
reliably_app/catalog/errors.py
reliably_app/catalog/models.py
reliably_app/catalog/schemas.py
reliably_app/catalog/service.py
reliably_app/catalog/validators.py
reliably_app/cli/__init__.py
reliably_app/cli/default.auto-install.env
reliably_app/cli/default.docker.env
reliably_app/cli/default.local.env
reliably_app/cli/pidfile.py
reliably_app/cli/reliably.service
reliably_app/config.py
reliably_app/crypto.py
reliably_app/data/__init__.py
reliably_app/data/catalog.json
reliably_app/data/experiments/__init__.py
reliably_app/data/experiments/login-page-availability.json
reliably_app/data/requirements.txt
reliably_app/data/templates/application-must-have-capacity.json
reliably_app/data/templates/endpoint-availability.json
reliably_app/database.py
reliably_app/dependencies/__init__.py
reliably_app/dependencies/auth.py
reliably_app/dependencies/database.py
reliably_app/dependencies/org.py
reliably_app/dependencies/scope.py
reliably_app/deployment/__init__.py
reliably_app/deployment/crud.py
reliably_app-0.5.0.dist-info/RECORD
