Metadata-Version: 2.1
Name: reliably-app
Version: 0.5.0
Summary: Reliably - Resilience and Chaos Engineering Platform
Author-Email: Sylvain Hellegouarch <sylvain@rebound.how>
License: Apache-2.0
Classifier: License :: OSI Approved :: Apache Software License
Classifier: Development Status :: 5 - Production/Stable
Classifier: Intended Audience :: Developers
Classifier: Operating System :: OS Independent
Classifier: Framework :: FastAPI
Classifier: Framework :: Pydantic :: 2
Classifier: Programming Language :: Python :: 3
Classifier: Programming Language :: Python :: 3.12
Classifier: Programming Language :: Python :: 3.13
Project-URL: Homepage, https://reliably.com/
Project-URL: Documentation, https://reliably.com/docs/
Project-URL: Source, https://github.com/rebound-how/reliably
Requires-Python: >=3.12
Requires-Dist: pydantic>=2.1.1
Requires-Dist: authlib>=1.2.1
Requires-Dist: httpx[http2]>=0.24.1
Requires-Dist: anyio>=3.7.1
Requires-Dist: itsdangerous>=2.1.2
Requires-Dist: asyncpg>=0.28.0
Requires-Dist: sqlalchemy[asyncio]>=1.4.49
Requires-Dist: fastapi>=0.100.1
Requires-Dist: opentelemetry-api>=1.19.0
Requires-Dist: opentelemetry-sdk>=1.19.0
Requires-Dist: opentelemetry-instrumentation-fastapi>=0.40b0
Requires-Dist: opentelemetry-instrumentation-sqlalchemy>=0.40b0
Requires-Dist: opentelemetry-instrumentation-httpx>=0.40b0
Requires-Dist: opentelemetry-instrumentation-logging>=0.40b0
Requires-Dist: opentelemetry-instrumentation-asyncpg>=0.40b0
Requires-Dist: opentelemetry-exporter-otlp-proto-http>=1.19.0
Requires-Dist: opentelemetry-propagator-b3>=1.19.0
Requires-Dist: opentelemetry-semantic-conventions>=0.40b0
Requires-Dist: python-json-logger>=2.0.7
Requires-Dist: cryptography>=41.0.2
Requires-Dist: ruamel-yaml>=0.17.32
Requires-Dist: greenlet>=2.0.2
Requires-Dist: orjson>=3.9.2
Requires-Dist: uvicorn>=0.23.2
Requires-Dist: httptools>=0.6.0
Requires-Dist: uvloop>=0.17.0
Requires-Dist: typer>=0.9.0
Requires-Dist: argon2-cffi>=21.3.0
Requires-Dist: docker>=6.1.3
Requires-Dist: croniter>=1.4.1
Requires-Dist: cron-validator>=1.0.8
Requires-Dist: kubernetes>=32.0.1
Requires-Dist: pydantic-settings>=2.0.2
Requires-Dist: pytz>=2023.3
Requires-Dist: certifi>=2023.7.22
Requires-Dist: magentic>=0.11.1
Requires-Dist: lueur>=0.1.0
Requires-Dist: python-jsonpath>=1.1.1
Requires-Dist: msgspec>=0.19.0
Requires-Dist: tenacity>=9.0.0
Requires-Dist: Secweb>=1.18.1
Requires-Dist: instructor>=1.7.2
Requires-Dist: alembic>=1.9.0
Requires-Dist: rich>=13.4.2
Requires-Dist: platformdirs>=4.3.6
Requires-Dist: tzlocal>=5.2
Requires-Dist: boto3>=1.36.18
